<?xml version="1.0" encoding="Windows-1252" standalone="no"?>
<AuditFile xmlns="urn:OECD:StandardAuditFile-Tax:PT_1.04_01" xmlns:xsi="http://www.w3.org/2001/XMLSchema-instance" xsi:schemaLocation="urn:OECD:StandardAuditFile-Tax:PT_1.04_01 ../schemas/SAF-T.xsd" xmlns:doc="urn:schemas-basda-org:schema-extensions:documentation">
	<Header>
		<AuditFileVersion>1.04_01</AuditFileVersion>
		<CompanyID>506426670</CompanyID>
		<TaxRegistrationNumber>506426670</TaxRegistrationNumber>
		<TaxAccountingBasis>I</TaxAccountingBasis>
		<CompanyName>Tech4You</CompanyName>
		<CompanyAddress>
			<BuildingNumber>857</BuildingNumber>
			<StreetName>Rua do Curral</StreetName>
			<AddressDetail>Rua do Curral, 857</AddressDetail>
			<City>Margaride</City>
			<PostalCode>4610-156</PostalCode>
			<Region>Porto</Region>
			<Country>PT</Country>
		</CompanyAddress>
		<FiscalYear>2019</FiscalYear>
		<StartDate>2019-01-01</StartDate>
		<EndDate>2019-12-31</EndDate>
		<CurrencyCode>EUR</CurrencyCode>
		<DateCreated>2020-07-16</DateCreated>
		<TaxEntity>Sede</TaxEntity>
		<ProductCompanyTaxID>503140600</ProductCompanyTaxID>
		<SoftwareCertificateNumber>0030</SoftwareCertificateNumber>
		<ProductID>ERP v750/PRIMAVERA Business Software Solutions</ProductID>
		<ProductVersion>09.1507.1039</ProductVersion>
		<Telephone>255314002</Telephone>
		<Fax>255314120</Fax>
		<Email>geral@tech4you.com</Email>
		<Website>www.tech4you.com</Website>
	</Header>
	<MasterFiles>
		<GeneralLedgerAccounts>
			<TaxonomyReference>S</TaxonomyReference>
			<Account>
				<AccountID>21</AccountID>
				<AccountDescription>Clientes</AccountDescription>
				<OpeningDebitBalance>0.00</OpeningDebitBalance>
				<OpeningCreditBalance>0.00</OpeningCreditBalance>
				<ClosingDebitBalance>19667.70</ClosingDebitBalance>
				<ClosingCreditBalance>0.00</ClosingCreditBalance>
				<GroupingCategory>GR</GroupingCategory>
			</Account>
			<Account>
				<AccountID>211</AccountID>
				<AccountDescription>Clientes c/c</AccountDescription>
				<OpeningDebitBalance>0.00</OpeningDebitBalance>
				<OpeningCreditBalance>0.00</OpeningCreditBalance>
				<ClosingDebitBalance>19667.70</ClosingDebitBalance>
				<ClosingCreditBalance>0.00</ClosingCreditBalance>
				<GroupingCategory>GA</GroupingCategory>
				<GroupingCode>21</GroupingCode>
			</Account>
			<Account>
				<AccountID>2111</AccountID>
				<AccountDescription>Clientes gerais</AccountDescription>
				<OpeningDebitBalance>0.00</OpeningDebitBalance>
				<OpeningCreditBalance>0.00</OpeningCreditBalance>
				<ClosingDebitBalance>19667.70</ClosingDebitBalance>
				<ClosingCreditBalance>0.00</ClosingCreditBalance>
				<GroupingCategory>GA</GroupingCategory>
				<GroupingCode>211</GroupingCode>
			</Account>
			<Account>
				<AccountID>21111</AccountID>
				<AccountDescription>Clientes - gr - mercado nacional</AccountDescription>
				<OpeningDebitBalance>0.00</OpeningDebitBalance>
				<OpeningCreditBalance>0.00</OpeningCreditBalance>
				<ClosingDebitBalance>19667.70</ClosingDebitBalance>
				<ClosingCreditBalance>0.00</ClosingCreditBalance>
				<GroupingCategory>GA</GroupingCategory>
				<GroupingCode>2111</GroupingCode>
			</Account>
			<Account>
				<AccountID>211110002</AccountID>
				<AccountDescription>Worten</AccountDescription>
				<OpeningDebitBalance>0.00</OpeningDebitBalance>
				<OpeningCreditBalance>0.00</OpeningCreditBalance>
				<ClosingDebitBalance>19667.70</ClosingDebitBalance>
				<ClosingCreditBalance>0.00</ClosingCreditBalance>
				<GroupingCategory>GM</GroupingCategory>
				<GroupingCode>21111</GroupingCode>
				<TaxonomyCode>10</TaxonomyCode>
			</Account>
			<Account>
				<AccountID>22</AccountID>
				<AccountDescription>Fornecedores</AccountDescription>
				<OpeningDebitBalance>0.00</OpeningDebitBalance>
				<OpeningCreditBalance>0.00</OpeningCreditBalance>
				<ClosingDebitBalance>0.00</ClosingDebitBalance>
				<ClosingCreditBalance>24230.61</ClosingCreditBalance>
				<GroupingCategory>GR</GroupingCategory>
			</Account>
			<Account>
				<AccountID>221</AccountID>
				<AccountDescription>Fornecedores c/c</AccountDescription>
				<OpeningDebitBalance>0.00</OpeningDebitBalance>
				<OpeningCreditBalance>0.00</OpeningCreditBalance>
				<ClosingDebitBalance>0.00</ClosingDebitBalance>
				<ClosingCreditBalance>24230.61</ClosingCreditBalance>
				<GroupingCategory>GA</GroupingCategory>
				<GroupingCode>22</GroupingCode>
			</Account>
			<Account>
				<AccountID>2211</AccountID>
				<AccountDescription>Fornecedores gerais</AccountDescription>
				<OpeningDebitBalance>0.00</OpeningDebitBalance>
				<OpeningCreditBalance>0.00</OpeningCreditBalance>
				<ClosingDebitBalance>0.00</ClosingDebitBalance>
				<ClosingCreditBalance>24230.61</ClosingCreditBalance>
				<GroupingCategory>GA</GroupingCategory>
				<GroupingCode>221</GroupingCode>
			</Account>
			<Account>
				<AccountID>22111</AccountID>
				<AccountDescription>Fornecedores - gr - mercado nacional</AccountDescription>
				<OpeningDebitBalance>0.00</OpeningDebitBalance>
				<OpeningCreditBalance>0.00</OpeningCreditBalance>
				<ClosingDebitBalance>0.00</ClosingDebitBalance>
				<ClosingCreditBalance>24230.61</ClosingCreditBalance>
				<GroupingCategory>GA</GroupingCategory>
				<GroupingCode>2211</GroupingCode>
			</Account>
			<Account>
				<AccountID>221110001</AccountID>
				<AccountDescription>Asus</AccountDescription>
				<OpeningDebitBalance>0.00</OpeningDebitBalance>
				<OpeningCreditBalance>0.00</OpeningCreditBalance>
				<ClosingDebitBalance>0.00</ClosingDebitBalance>
				<ClosingCreditBalance>24230.61</ClosingCreditBalance>
				<GroupingCategory>GM</GroupingCategory>
				<GroupingCode>22111</GroupingCode>
				<TaxonomyCode>37</TaxonomyCode>
			</Account>
			<Account>
				<AccountID>24</AccountID>
				<AccountDescription>Estado e outros entes públicos</AccountDescription>
				<OpeningDebitBalance>0.00</OpeningDebitBalance>
				<OpeningCreditBalance>0.00</OpeningCreditBalance>
				<ClosingDebitBalance>4530.93</ClosingDebitBalance>
				<ClosingCreditBalance>3677.70</ClosingCreditBalance>
				<GroupingCategory>GR</GroupingCategory>
			</Account>
			<Account>
				<AccountID>243</AccountID>
				<AccountDescription>Imposto sobre o valor acrescentado (IVA)</AccountDescription>
				<OpeningDebitBalance>0.00</OpeningDebitBalance>
				<OpeningCreditBalance>0.00</OpeningCreditBalance>
				<ClosingDebitBalance>4530.93</ClosingDebitBalance>
				<ClosingCreditBalance>3677.70</ClosingCreditBalance>
				<GroupingCategory>GA</GroupingCategory>
				<GroupingCode>24</GroupingCode>
			</Account>
			<Account>
				<AccountID>2432</AccountID>
				<AccountDescription>Iva - Dedutível</AccountDescription>
				<OpeningDebitBalance>0.00</OpeningDebitBalance>
				<OpeningCreditBalance>0.00</OpeningCreditBalance>
				<ClosingDebitBalance>4530.93</ClosingDebitBalance>
				<ClosingCreditBalance>0.00</ClosingCreditBalance>
				<GroupingCategory>GA</GroupingCategory>
				<GroupingCode>243</GroupingCode>
			</Account>
			<Account>
				<AccountID>24321</AccountID>
				<AccountDescription>Existências</AccountDescription>
				<OpeningDebitBalance>0.00</OpeningDebitBalance>
				<OpeningCreditBalance>0.00</OpeningCreditBalance>
				<ClosingDebitBalance>4530.93</ClosingDebitBalance>
				<ClosingCreditBalance>0.00</ClosingCreditBalance>
				<GroupingCategory>GA</GroupingCategory>
				<GroupingCode>2432</GroupingCode>
			</Account>
			<Account>
				<AccountID>243211</AccountID>
				<AccountDescription>Existências Continente</AccountDescription>
				<OpeningDebitBalance>0.00</OpeningDebitBalance>
				<OpeningCreditBalance>0.00</OpeningCreditBalance>
				<ClosingDebitBalance>4530.93</ClosingDebitBalance>
				<ClosingCreditBalance>0.00</ClosingCreditBalance>
				<GroupingCategory>GA</GroupingCategory>
				<GroupingCode>24321</GroupingCode>
			</Account>
			<Account>
				<AccountID>2432113</AccountID>
				<AccountDescription>Ex. - Taxa Normal</AccountDescription>
				<OpeningDebitBalance>0.00</OpeningDebitBalance>
				<OpeningCreditBalance>0.00</OpeningCreditBalance>
				<ClosingDebitBalance>4530.93</ClosingDebitBalance>
				<ClosingCreditBalance>0.00</ClosingCreditBalance>
				<GroupingCategory>GA</GroupingCategory>
				<GroupingCode>243211</GroupingCode>
			</Account>
			<Account>
				<AccountID>243211323</AccountID>
				<AccountDescription>Ex. - Taxa Normal-Tx.23%</AccountDescription>
				<OpeningDebitBalance>0.00</OpeningDebitBalance>
				<OpeningCreditBalance>0.00</OpeningCreditBalance>
				<ClosingDebitBalance>4530.93</ClosingDebitBalance>
				<ClosingCreditBalance>0.00</ClosingCreditBalance>
				<GroupingCategory>GA</GroupingCategory>
				<GroupingCode>2432113</GroupingCode>
			</Account>
			<Account>
				<AccountID>2432113231</AccountID>
				<AccountDescription>Ex. - Tx. Nm. - Mercado Nacional</AccountDescription>
				<OpeningDebitBalance>0.00</OpeningDebitBalance>
				<OpeningCreditBalance>0.00</OpeningCreditBalance>
				<ClosingDebitBalance>4530.93</ClosingDebitBalance>
				<ClosingCreditBalance>0.00</ClosingCreditBalance>
				<GroupingCategory>GA</GroupingCategory>
				<GroupingCode>243211323</GroupingCode>
			</Account>
			<Account>
				<AccountID>24321132311</AccountID>
				<AccountDescription>Ex. Tx. Nm.- MN-TT/Dedutível</AccountDescription>
				<OpeningDebitBalance>0.00</OpeningDebitBalance>
				<OpeningCreditBalance>0.00</OpeningCreditBalance>
				<ClosingDebitBalance>4530.93</ClosingDebitBalance>
				<ClosingCreditBalance>0.00</ClosingCreditBalance>
				<GroupingCategory>GM</GroupingCategory>
				<GroupingCode>2432113231</GroupingCode>
				<TaxonomyCode>74</TaxonomyCode>
			</Account>
			<Account>
				<AccountID>2433</AccountID>
				<AccountDescription>Iva - Liquidado</AccountDescription>
				<OpeningDebitBalance>0.00</OpeningDebitBalance>
				<OpeningCreditBalance>0.00</OpeningCreditBalance>
				<ClosingDebitBalance>0.00</ClosingDebitBalance>
				<ClosingCreditBalance>3677.70</ClosingCreditBalance>
				<GroupingCategory>GA</GroupingCategory>
				<GroupingCode>243</GroupingCode>
			</Account>
			<Account>
				<AccountID>24331</AccountID>
				<AccountDescription>Operacoes Gerais</AccountDescription>
				<OpeningDebitBalance>0.00</OpeningDebitBalance>
				<OpeningCreditBalance>0.00</OpeningCreditBalance>
				<ClosingDebitBalance>0.00</ClosingDebitBalance>
				<ClosingCreditBalance>3677.70</ClosingCreditBalance>
				<GroupingCategory>GA</GroupingCategory>
				<GroupingCode>2433</GroupingCode>
			</Account>
			<Account>
				<AccountID>243311</AccountID>
				<AccountDescription>Iva Liq. - Vendas</AccountDescription>
				<OpeningDebitBalance>0.00</OpeningDebitBalance>
				<OpeningCreditBalance>0.00</OpeningCreditBalance>
				<ClosingDebitBalance>0.00</ClosingDebitBalance>
				<ClosingCreditBalance>3677.70</ClosingCreditBalance>
				<GroupingCategory>GA</GroupingCategory>
				<GroupingCode>24331</GroupingCode>
			</Account>
			<Account>
				<AccountID>2433111</AccountID>
				<AccountDescription>Iva Liq. - Vendas-Continente</AccountDescription>
				<OpeningDebitBalance>0.00</OpeningDebitBalance>
				<OpeningCreditBalance>0.00</OpeningCreditBalance>
				<ClosingDebitBalance>0.00</ClosingDebitBalance>
				<ClosingCreditBalance>3677.70</ClosingCreditBalance>
				<GroupingCategory>GA</GroupingCategory>
				<GroupingCode>243311</GroupingCode>
			</Account>
			<Account>
				<AccountID>24331113</AccountID>
				<AccountDescription>Iva Liq. - Taxa Normal</AccountDescription>
				<OpeningDebitBalance>0.00</OpeningDebitBalance>
				<OpeningCreditBalance>0.00</OpeningCreditBalance>
				<ClosingDebitBalance>0.00</ClosingDebitBalance>
				<ClosingCreditBalance>3677.70</ClosingCreditBalance>
				<GroupingCategory>GA</GroupingCategory>
				<GroupingCode>2433111</GroupingCode>
			</Account>
			<Account>
				<AccountID>2433111323</AccountID>
				<AccountDescription>Iva Liq. - Taxa Normal-Tx.23%</AccountDescription>
				<OpeningDebitBalance>0.00</OpeningDebitBalance>
				<OpeningCreditBalance>0.00</OpeningCreditBalance>
				<ClosingDebitBalance>0.00</ClosingDebitBalance>
				<ClosingCreditBalance>3677.70</ClosingCreditBalance>
				<GroupingCategory>GA</GroupingCategory>
				<GroupingCode>24331113</GroupingCode>
			</Account>
			<Account>
				<AccountID>24331113231</AccountID>
				<AccountDescription>Iva Liq.- Tx. Nm.- Mercado Nacional</AccountDescription>
				<OpeningDebitBalance>0.00</OpeningDebitBalance>
				<OpeningCreditBalance>0.00</OpeningCreditBalance>
				<ClosingDebitBalance>0.00</ClosingDebitBalance>
				<ClosingCreditBalance>3677.70</ClosingCreditBalance>
				<GroupingCategory>GM</GroupingCategory>
				<GroupingCode>2433111323</GroupingCode>
				<TaxonomyCode>75</TaxonomyCode>
			</Account>
			<Account>
				<AccountID>31</AccountID>
				<AccountDescription>Compras</AccountDescription>
				<OpeningDebitBalance>0.00</OpeningDebitBalance>
				<OpeningCreditBalance>0.00</OpeningCreditBalance>
				<ClosingDebitBalance>19699.68</ClosingDebitBalance>
				<ClosingCreditBalance>0.00</ClosingCreditBalance>
				<GroupingCategory>GR</GroupingCategory>
			</Account>
			<Account>
				<AccountID>311</AccountID>
				<AccountDescription>Mercadorias</AccountDescription>
				<OpeningDebitBalance>0.00</OpeningDebitBalance>
				<OpeningCreditBalance>0.00</OpeningCreditBalance>
				<ClosingDebitBalance>19699.68</ClosingDebitBalance>
				<ClosingCreditBalance>0.00</ClosingCreditBalance>
				<GroupingCategory>GA</GroupingCategory>
				<GroupingCode>31</GroupingCode>
			</Account>
			<Account>
				<AccountID>3111</AccountID>
				<AccountDescription>Compras-merc.-mercado nacional</AccountDescription>
				<OpeningDebitBalance>0.00</OpeningDebitBalance>
				<OpeningCreditBalance>0.00</OpeningCreditBalance>
				<ClosingDebitBalance>19699.68</ClosingDebitBalance>
				<ClosingCreditBalance>0.00</ClosingCreditBalance>
				<GroupingCategory>GM</GroupingCategory>
				<GroupingCode>311</GroupingCode>
				<TaxonomyCode>156</TaxonomyCode>
			</Account>
			<Account>
				<AccountID>71</AccountID>
				<AccountDescription>Vendas</AccountDescription>
				<OpeningDebitBalance>0.00</OpeningDebitBalance>
				<OpeningCreditBalance>0.00</OpeningCreditBalance>
				<ClosingDebitBalance>0.00</ClosingDebitBalance>
				<ClosingCreditBalance>15990.00</ClosingCreditBalance>
				<GroupingCategory>GR</GroupingCategory>
			</Account>
			<Account>
				<AccountID>711</AccountID>
				<AccountDescription>Mercadorias</AccountDescription>
				<OpeningDebitBalance>0.00</OpeningDebitBalance>
				<OpeningCreditBalance>0.00</OpeningCreditBalance>
				<ClosingDebitBalance>0.00</ClosingDebitBalance>
				<ClosingCreditBalance>15990.00</ClosingCreditBalance>
				<GroupingCategory>GA</GroupingCategory>
				<GroupingCode>71</GroupingCode>
			</Account>
			<Account>
				<AccountID>7111</AccountID>
				<AccountDescription>Vendas-merc.-mercado nacional</AccountDescription>
				<OpeningDebitBalance>0.00</OpeningDebitBalance>
				<OpeningCreditBalance>0.00</OpeningCreditBalance>
				<ClosingDebitBalance>0.00</ClosingDebitBalance>
				<ClosingCreditBalance>15990.00</ClosingCreditBalance>
				<GroupingCategory>GM</GroupingCategory>
				<GroupingCode>711</GroupingCode>
				<TaxonomyCode>506</TaxonomyCode>
			</Account>
		</GeneralLedgerAccounts>
		<Customer>
			<CustomerID>Consumidor final</CustomerID>
			<AccountID>Desconhecido</AccountID>
			<CustomerTaxID>999999990</CustomerTaxID>
			<CompanyName>Consumidor final</CompanyName>
			<BillingAddress>
				<AddressDetail>Desconhecido</AddressDetail>
				<City>Desconhecido</City>
				<PostalCode>Desconhecido</PostalCode>
				<Country>Desconhecido</Country>
			</BillingAddress>
			<ShipToAddress>
				<AddressDetail>Desconhecido</AddressDetail>
				<City>Desconhecido</City>
				<PostalCode>Desconhecido</PostalCode>
				<Country>Desconhecido</Country>
			</ShipToAddress>
			<SelfBillingIndicator>0</SelfBillingIndicator>
		</Customer>
		<Customer>
			<CustomerID>PT509045200_C</CustomerID>
			<AccountID>211110002</AccountID>
			<CustomerTaxID>509045200</CustomerTaxID>
			<CompanyName>Worten</CompanyName>
			<BillingAddress>
				<AddressDetail>Senhora da Hora</AddressDetail>
				<City>Sara Afonso</City>
				<PostalCode>4460-851</PostalCode>
				<Region>Porto</Region>
				<Country>PT</Country>
			</BillingAddress>
			<ShipToAddress>
				<AddressDetail>Senhora da Hora</AddressDetail>
				<City>Sara Afonso</City>
				<PostalCode>4460-851</PostalCode>
				<Region>Porto</Region>
				<Country>PT</Country>
			</ShipToAddress>
			<Telephone>+351 229 571 300</Telephone>
			<Fax>+351 229 571 301</Fax>
			<Website>www.wortennorteshop.pt</Website>
			<SelfBillingIndicator>0</SelfBillingIndicator>
		</Customer>
		<Supplier>
			<SupplierID>507501055_F</SupplierID>
			<AccountID>221110001</AccountID>
			<SupplierTaxID>507501055</SupplierTaxID>
			<CompanyName>Asus</CompanyName>
			<BillingAddress>
				<AddressDetail>Rua François Guichard</AddressDetail>
				<City>Bessa</City>
				<PostalCode>4100-012</PostalCode>
				<Region>Porto</Region>
				<Country>PT</Country>
			</BillingAddress>
			<ShipFromAddress>
				<AddressDetail>Rua François Guichard</AddressDetail>
				<City>Bessa</City>
				<PostalCode>4100-012</PostalCode>
				<Region>Porto</Region>
				<Country>PT</Country>
			</ShipFromAddress>
			<Telephone>+351 505 677 139</Telephone>
			<Fax>+351 505 678 128</Fax>
			<Website>www.asussupport.com.pt</Website>
			<SelfBillingIndicator>0</SelfBillingIndicator>
		</Supplier>
		<Product>
			<ProductType>P</ProductType>
			<ProductCode>A00021</ProductCode>
			<ProductGroup>Portateis</ProductGroup>
			<ProductDescription>ROG Zephyrus G14</ProductDescription>
			<ProductNumberCode>A00021</ProductNumberCode>
		</Product>
		<Product>
			<ProductType>O</ProductType>
			<ProductCode>Especial</ProductCode>
			<ProductGroup>Sem família</ProductGroup>
			<ProductDescription>Linha especial</ProductDescription>
			<ProductNumberCode>Especial</ProductNumberCode>
		</Product>
		<TaxTable>
			<TaxTableEntry>
				<TaxType>IVA</TaxType>
				<TaxCountryRegion>PT</TaxCountryRegion>
				<TaxCode>ISE</TaxCode>
				<Description>Isenta</Description>
				<TaxPercentage>0.00</TaxPercentage>
			</TaxTableEntry>
			<TaxTableEntry>
				<TaxType>IVA</TaxType>
				<TaxCountryRegion>PT</TaxCountryRegion>
				<TaxCode>OUT</TaxCode>
				<Description>Outras</Description>
				<TaxPercentage>4.00</TaxPercentage>
			</TaxTableEntry>
			<TaxTableEntry>
				<TaxType>IVA</TaxType>
				<TaxCountryRegion>PT</TaxCountryRegion>
				<TaxCode>RED</TaxCode>
				<Description>Reduzida</Description>
				<TaxPercentage>5.00</TaxPercentage>
			</TaxTableEntry>
			<TaxTableEntry>
				<TaxType>IVA</TaxType>
				<TaxCountryRegion>PT</TaxCountryRegion>
				<TaxCode>RED</TaxCode>
				<Description>Reduzida</Description>
				<TaxPercentage>6.00</TaxPercentage>
			</TaxTableEntry>
			<TaxTableEntry>
				<TaxType>IVA</TaxType>
				<TaxCountryRegion>PT</TaxCountryRegion>
				<TaxCode>OUT</TaxCode>
				<Description>Outras</Description>
				<TaxPercentage>9.00</TaxPercentage>
			</TaxTableEntry>
			<TaxTableEntry>
				<TaxType>IVA</TaxType>
				<TaxCountryRegion>PT</TaxCountryRegion>
				<TaxCode>INT</TaxCode>
				<Description>Intermédia</Description>
				<TaxPercentage>12.00</TaxPercentage>
			</TaxTableEntry>
			<TaxTableEntry>
				<TaxType>IVA</TaxType>
				<TaxCountryRegion>PT</TaxCountryRegion>
				<TaxCode>INT</TaxCode>
				<Description>Intermédia</Description>
				<TaxPercentage>13.00</TaxPercentage>
			</TaxTableEntry>
			<TaxTableEntry>
				<TaxType>IVA</TaxType>
				<TaxCountryRegion>PT</TaxCountryRegion>
				<TaxCode>OUT</TaxCode>
				<Description>Outras</Description>
				<TaxPercentage>15.00</TaxPercentage>
			</TaxTableEntry>
			<TaxTableEntry>
				<TaxType>IVA</TaxType>
				<TaxCountryRegion>PT</TaxCountryRegion>
				<TaxCode>OUT</TaxCode>
				<Description>Outras</Description>
				<TaxPercentage>22.00</TaxPercentage>
			</TaxTableEntry>
			<TaxTableEntry>
				<TaxType>IVA</TaxType>
				<TaxCountryRegion>PT</TaxCountryRegion>
				<TaxCode>NOR</TaxCode>
				<Description>Normal</Description>
				<TaxPercentage>23.00</TaxPercentage>
			</TaxTableEntry>
			<TaxTableEntry>
				<TaxType>IVA</TaxType>
				<TaxCountryRegion>PT</TaxCountryRegion>
				<TaxCode>OUT</TaxCode>
				<Description>Outras</Description>
				<TaxPercentage>23.00</TaxPercentage>
			</TaxTableEntry>
			<TaxTableEntry>
				<TaxType>IVA</TaxType>
				<TaxCountryRegion>PT-AC</TaxCountryRegion>
				<TaxCode>ISE</TaxCode>
				<Description>Isenta</Description>
				<TaxPercentage>0.00</TaxPercentage>
			</TaxTableEntry>
			<TaxTableEntry>
				<TaxType>IVA</TaxType>
				<TaxCountryRegion>PT-AC</TaxCountryRegion>
				<TaxCode>OUT</TaxCode>
				<Description>Outras</Description>
				<TaxPercentage>4.00</TaxPercentage>
			</TaxTableEntry>
			<TaxTableEntry>
				<TaxType>IVA</TaxType>
				<TaxCountryRegion>PT-AC</TaxCountryRegion>
				<TaxCode>OUT</TaxCode>
				<Description>Outras</Description>
				<TaxPercentage>9.00</TaxPercentage>
			</TaxTableEntry>
			<TaxTableEntry>
				<TaxType>IVA</TaxType>
				<TaxCountryRegion>PT-AC</TaxCountryRegion>
				<TaxCode>OUT</TaxCode>
				<Description>Outras</Description>
				<TaxPercentage>16.00</TaxPercentage>
			</TaxTableEntry>
			<TaxTableEntry>
				<TaxType>IVA</TaxType>
				<TaxCountryRegion>PT-MA</TaxCountryRegion>
				<TaxCode>ISE</TaxCode>
				<Description>Isenta</Description>
				<TaxPercentage>0.00</TaxPercentage>
			</TaxTableEntry>
			<TaxTableEntry>
				<TaxType>IVA</TaxType>
				<TaxCountryRegion>PT-MA</TaxCountryRegion>
				<TaxCode>OUT</TaxCode>
				<Description>Outras</Description>
				<TaxPercentage>5.00</TaxPercentage>
			</TaxTableEntry>
			<TaxTableEntry>
				<TaxType>IVA</TaxType>
				<TaxCountryRegion>PT-MA</TaxCountryRegion>
				<TaxCode>OUT</TaxCode>
				<Description>Outras</Description>
				<TaxPercentage>12.00</TaxPercentage>
			</TaxTableEntry>
			<TaxTableEntry>
				<TaxType>IVA</TaxType>
				<TaxCountryRegion>PT-MA</TaxCountryRegion>
				<TaxCode>OUT</TaxCode>
				<Description>Outras</Description>
				<TaxPercentage>22.00</TaxPercentage>
			</TaxTableEntry>
			<TaxTableEntry>
				<TaxType>IS</TaxType>
				<TaxCountryRegion>PT</TaxCountryRegion>
				<TaxCode>ISE</TaxCode>
				<Description>Isento</Description>
				<TaxPercentage>0.00</TaxPercentage>
			</TaxTableEntry>
		</TaxTable>
	</MasterFiles>
	<GeneralLedgerEntries>
		<NumberOfEntries>2</NumberOfEntries>
		<TotalDebit>43898.31</TotalDebit>
		<TotalCredit>43898.31</TotalCredit>
		<Journal>
			<JournalID>00041</JournalID>
			<Description>Compras - MN</Description>
			<Transaction>
				<TransactionID>2019-01-12 00041 10001</TransactionID>
				<Period>1</Period>
				<TransactionDate>2019-01-12</TransactionDate>
				<SourceID>estg</SourceID>
				<Description>VFA Nº 1/C</Description>
				<DocArchivalNumber>10001</DocArchivalNumber>
				<TransactionType>N</TransactionType>
				<GLPostingDate>2020-07-16</GLPostingDate>
				<Lines>
					<CreditLine>
						<RecordID>1</RecordID>
						<AccountID>221110001</AccountID>
						<SourceDocumentID>VFA C/1</SourceDocumentID>
						<SystemEntryDate>2020-07-16T10:50:22</SystemEntryDate>
						<Description>VFA Nº 1/C</Description>
						<CreditAmount>24230.61</CreditAmount>
					</CreditLine>
					<DebitLine>
						<RecordID>2</RecordID>
						<AccountID>3111</AccountID>
						<SourceDocumentID>VFA C/1</SourceDocumentID>
						<SystemEntryDate>2020-07-16T10:50:22</SystemEntryDate>
						<Description>VFA Nº 1/C</Description>
						<DebitAmount>19699.68</DebitAmount>
					</DebitLine>
					<DebitLine>
						<RecordID>3</RecordID>
						<AccountID>24321132311</AccountID>
						<SourceDocumentID>VFA C/1</SourceDocumentID>
						<SystemEntryDate>2020-07-16T10:50:22</SystemEntryDate>
						<Description>VFA Nº 1/C</Description>
						<DebitAmount>4530.93</DebitAmount>
					</DebitLine>
				</Lines>
			</Transaction>
		</Journal>
		<Journal>
			<JournalID>00051</JournalID>
			<Description>Vendas - Crédito - MN</Description>
			<Transaction>
				<TransactionID>2019-01-14 00051 10001</TransactionID>
				<Period>1</Period>
				<TransactionDate>2019-01-14</TransactionDate>
				<SourceID>estg</SourceID>
				<Description>FA Nº 1/C</Description>
				<DocArchivalNumber>10001</DocArchivalNumber>
				<TransactionType>N</TransactionType>
				<GLPostingDate>2020-07-16</GLPostingDate>
				<Lines>
					<DebitLine>
						<RecordID>1</RecordID>
						<AccountID>211110002</AccountID>
						<SourceDocumentID>FA C/1</SourceDocumentID>
						<SystemEntryDate>2020-07-16T10:53:27</SystemEntryDate>
						<Description>FA Nº 1/C</Description>
						<DebitAmount>19667.70</DebitAmount>
					</DebitLine>
					<CreditLine>
						<RecordID>2</RecordID>
						<AccountID>7111</AccountID>
						<SourceDocumentID>FA C/1</SourceDocumentID>
						<SystemEntryDate>2020-07-16T10:53:27</SystemEntryDate>
						<Description>FA Nº 1/C</Description>
						<CreditAmount>15990.00</CreditAmount>
					</CreditLine>
					<CreditLine>
						<RecordID>3</RecordID>
						<AccountID>24331113231</AccountID>
						<SourceDocumentID>FA C/1</SourceDocumentID>
						<SystemEntryDate>2020-07-16T10:53:27</SystemEntryDate>
						<Description>FA Nº 1/C</Description>
						<CreditAmount>3677.70</CreditAmount>
					</CreditLine>
				</Lines>
			</Transaction>
		</Journal>
	</GeneralLedgerEntries>
	<SourceDocuments>
		<SalesInvoices>
			<NumberOfEntries>1</NumberOfEntries>
			<TotalDebit>0.00</TotalDebit>
			<TotalCredit>15990.00</TotalCredit>
			<Invoice>
				<InvoiceNo>FA C/1</InvoiceNo>
				<ATCUD>0</ATCUD>
				<DocumentStatus>
					<InvoiceStatus>N</InvoiceStatus>
					<InvoiceStatusDate>2020-07-16T10:53:25</InvoiceStatusDate>
					<SourceID>ESTG</SourceID>
					<SourceBilling>P</SourceBilling>
				</DocumentStatus>
				<Hash>L5UPNSuG4OWVMLK4k99SYIyvXYxgVk98RKxPvelOQg0BSRt4ShcBo3EShOyLEPjZWIFx1kaAlVkMSo7Om6c3T0EOKf7Y/KBvBYUMwKPxTMue1D37hLrbCX9ABszhR9SzcNgRsCm1A3AhNvK7dKhpC9iNsL/spGO7MNZlyIR4O8U=</Hash>
				<HashControl>1</HashControl>
				<Period>01</Period>
				<InvoiceDate>2019-01-14</InvoiceDate>
				<InvoiceType>FT</InvoiceType>
				<SpecialRegimes>
					<SelfBillingIndicator>0</SelfBillingIndicator>
					<CashVATSchemeIndicator>0</CashVATSchemeIndicator>
					<ThirdPartiesBillingIndicator>0</ThirdPartiesBillingIndicator>
				</SpecialRegimes>
				<SourceID>ESTG</SourceID>
				<SystemEntryDate>2020-07-16T10:53:25</SystemEntryDate>
				<TransactionID>2019-01-14 00051 10001</TransactionID>
				<CustomerID>PT509045200_C</CustomerID>
				<ShipTo>
					<DeliveryDate>2020-07-16</DeliveryDate>
					<Address>
						<AddressDetail>Senhora da Hora</AddressDetail>
						<City>Sara Afonso</City>
						<PostalCode>4460-851</PostalCode>
						<Country>PT</Country>
					</Address>
				</ShipTo>
				<ShipFrom>
					<DeliveryDate>2020-07-16</DeliveryDate>
					<Address>
						<AddressDetail>Rua do Curral, 857 - 0</AddressDetail>
						<City>Margaride</City>
						<PostalCode>4610-156</PostalCode>
						<Country>PT</Country>
					</Address>
				</ShipFrom>
				<MovementStartTime>2020-07-16T10:55:00</MovementStartTime>
				<Line>
					<LineNumber>1</LineNumber>
					<ProductCode>A00021</ProductCode>
					<ProductDescription>ROG Zephyrus G14</ProductDescription>
					<Quantity>10</Quantity>
					<UnitOfMeasure>UN</UnitOfMeasure>
					<UnitPrice>1599</UnitPrice>
					<TaxPointDate>2019-01-14</TaxPointDate>
					<Description>ROG Zephyrus G14</Description>
					<CreditAmount>15990.00</CreditAmount>
					<Tax>
						<TaxType>IVA</TaxType>
						<TaxCountryRegion>PT</TaxCountryRegion>
						<TaxCode>NOR</TaxCode>
						<TaxPercentage>23.00</TaxPercentage>
					</Tax>
					<SettlementAmount>0.00</SettlementAmount>
				</Line>
				<DocumentTotals>
					<TaxPayable>3677.70</TaxPayable>
					<NetTotal>15990.00</NetTotal>
					<GrossTotal>19667.70</GrossTotal>
				</DocumentTotals>
				<WithholdingTax>
					<WithholdingTaxAmount>0.00</WithholdingTaxAmount>
				</WithholdingTax>
			</Invoice>
		</SalesInvoices>
	</SourceDocuments>
</AuditFile>